rtui/__init__.py
rtui/app.py
rtui/astoria.py
rtui/commands/__init__.py
rtui/commands/command.py
rtui/commands/help.py
rtui/commands/kill.py
rtui/commands/metadata.py
rtui/commands/quit.py
rtui/commands/restart.py
rtui/commands/start.py
rtui/parser.py
rtui/tui.py
rtui/validator.py
rtui-0.1.1.dist-info/entry_points.txt
rtui-0.1.1.dist-info/LICENSE
rtui-0.1.1.dist-info/WHEEL
rtui-0.1.1.dist-info/METADATA
rtui-0.1.1.dist-info/RECORD
