Metadata-Version: 2.1
Name: rtui
Version: 0.1.1
Summary: Robot Terminal User Interface for Student Robotics Kit
Home-page: https://github.com/srobo/robot-tui
License: MIT
Author: Dan Trickey
Author-email: srobo-rtui@trickey.io
Requires-Python: >=3.8,<4.0
Classifier: License :: OSI Approved :: MIT License
Classifier: Programming Language :: Python :: 3
Classifier: Programming Language :: Python :: 3.8
Classifier: Programming Language :: Python :: 3.9
Classifier: Programming Language :: Python :: 3.10
Classifier: Programming Language :: Python :: 3.11
Classifier: Topic :: Software Development :: Libraries :: Python Modules
Classifier: Typing :: Typed
Requires-Dist: astoria (>=0.11.1,<0.12.0)
Requires-Dist: prompt-toolkit (>=3.0.31,<4.0.0)
Project-URL: Repository, https://github.com/srobo/robot-tui
